PyADSNewVersionAlpha/__init__.py
PyADSNewVersionAlpha/create.py
PyADSNewVersionAlpha/eltPackage.py
PyADSNewVersionAlpha/eltProject.py
PyADSNewVersionAlpha/eltSnap_Project_HTML.py
PyADSNewVersionAlpha/html/HTML_template.html
PyADSNewVersionAlpha/html/eltstyle.css
PyADSNewVersionAlpha/html/bootstrap-4.3.1-dist/css/bootstrap-grid.css
PyADSNewVersionAlpha/html/bootstrap-4.3.1-dist/css/bootstrap-grid.css.map
PyADSNewVersionAlpha/html/bootstrap-4.3.1-dist/css/bootstrap-grid.min.css
PyADSNewVersionAlpha/html/bootstrap-4.3.1-dist/css/bootstrap-grid.min.css.map
PyADSNewVersionAlpha/html/bootstrap-4.3.1-dist/css/bootstrap-reboot.css
PyADSNewVersionAlpha/html/bootstrap-4.3.1-dist/css/bootstrap-reboot.css.map
PyADSNewVersionAlpha/html/bootstrap-4.3.1-dist/css/bootstrap-reboot.min.css
PyADSNewVersionAlpha/html/bootstrap-4.3.1-dist/css/bootstrap.css
PyADSNewVersionAlpha/html/bootstrap-4.3.1-dist/css/bootstrap.css.map
PyADSNewVersionAlpha/html/bootstrap-4.3.1-dist/css/bootstrap.min.css
PyADSNewVersionAlpha/html/bootstrap-4.3.1-dist/css/bootstrap.min.css.map
PyADSNewVersionAlpha/html/bootstrap-4.3.1-dist/js/bootstrap.bundle.js
PyADSNewVersionAlpha/html/bootstrap-4.3.1-dist/js/bootstrap.bundle.js.map
PyADSNewVersionAlpha/html/bootstrap-4.3.1-dist/js/bootstrap.bundle.min.js
PyADSNewVersionAlpha/html/bootstrap-4.3.1-dist/js/bootstrap.bundle.min.js.map
PyADSNewVersionAlpha/html/bootstrap-4.3.1-dist/js/bootstrap.js
PyADSNewVersionAlpha/html/bootstrap-4.3.1-dist/js/bootstrap.js.map
PyADSNewVersionAlpha/html/bootstrap-4.3.1-dist/js/bootstrap.min.js
PyADSNewVersionAlpha/html/bootstrap-4.3.1-dist/js/bootstrap.min.js.map
PyADSNewVersionAlpha/html/images/eltSnap_whiteTransparent.png
eltsnap-0.1.1.dist-info/METADATA
eltsnap-0.1.1.dist-info/WHEEL
eltsnap-0.1.1.dist-info/top_level.txt
eltsnap-0.1.1.dist-info/RECORD
