Metadata-Version: 2.1
Name: eltsnap
Version: 0.1.1
Summary: Third version test
Home-page: https://github.com/Jim-BITracks/eltSnap-Python
Author: Jim Miller
License: MIT license
Platform: UNKNOWN
Classifier: Programming Language :: Python :: 3
Requires-Dist: pyodbc
Requires-Dist: jinja2
Requires-Dist: tabulate
